{"name": "forbidden-light", "displayName": "Forbidden Light", "id": "sm6", "cards": [{"name": "Exeggcute", "image": "https://images.pokemontcg.io/sm6/1.png", "number": "1", "supertype": "Pokémon", "rarity": "Common"}, {"name": "Alolan Exeggutor", "image": "https://images.pokemontcg.io/sm6/2.png", "number": "2", "supertype": "Pokémon", "rarity": "Common"}, {"name": "Snover", "image": "https://images.pokemontcg.io/sm6/3.png", "number": "3", "supertype": "Pokémon", "rarity": "Common"}, {"name": "Abomasnow", "image": "https://images.pokemontcg.io/sm6/4.png", "number": "4", "supertype": "Pokémon", "rarity": "Common"}, {"name": "Scatterbug", "image": "https://images.pokemontcg.io/sm6/5.png", "number": "5", "supertype": "Pokémon", "rarity": "Common"}, {"name": "Scatterbug", "image": "https://images.pokemontcg.io/sm6/6.png", "number": "6", "supertype": "Pokémon", "rarity": "Common"}, {"name": "Spewpa", "image": "https://images.pokemontcg.io/sm6/7.png", "number": "7", "supertype": "Pokémon", "rarity": "Common"}, {"name": "Vivillon", "image": "https://images.pokemontcg.io/sm6/8.png", "number": "8", "supertype": "Pokémon", "rarity": "Common"}, {"name": "Skiddo", "image": "https://images.pokemontcg.io/sm6/9.png", "number": "9", "supertype": "Pokémon", "rarity": "Common"}, {"name": "Gogoat", "image": "https://images.pokemontcg.io/sm6/10.png", "number": "10", "supertype": "Pokémon", "rarity": "Common"}, {"name": "Pheromosa", "image": "https://images.pokemontcg.io/sm6/11.png", "number": "11", "supertype": "Pokémon", "rarity": "Common"}, {"name": "Alolan Marowak", "image": "https://images.pokemontcg.io/sm6/12.png", "number": "12", "supertype": "Pokémon", "rarity": "Common"}, {"name": "Heatran", "image": "https://images.pokemontcg.io/sm6/13.png", "number": "13", "supertype": "Pokémon", "rarity": "Common"}, {"name": "Fennekin", "image": "https://images.pokemontcg.io/sm6/14.png", "number": "14", "supertype": "Pokémon", "rarity": "Common"}, {"name": "Fennekin", "image": "https://images.pokemontcg.io/sm6/15.png", "number": "15", "supertype": "Pokémon", "rarity": "Common"}, {"name": "Braixen", "image": "https://images.pokemontcg.io/sm6/16.png", "number": "16", "supertype": "Pokémon", "rarity": "Common"}, {"name": "Delphox", "image": "https://images.pokemontcg.io/sm6/17.png", "number": "17", "supertype": "Pokémon", "rarity": "Common"}, {"name": "Litleo", "image": "https://images.pokemontcg.io/sm6/18.png", "number": "18", "supertype": "Pokémon", "rarity": "Common"}, {"name": "Pyroar", "image": "https://images.pokemontcg.io/sm6/19.png", "number": "19", "supertype": "Pokémon", "rarity": "Common"}, {"name": "Palkia GX", "image": "https://images.pokemontcg.io/sm6/20.png", "number": "20", "supertype": "Pokémon", "rarity": "Common"}, {"name": "Froakie", "image": "https://images.pokemontcg.io/sm6/21.png", "number": "21", "supertype": "Pokémon", "rarity": "Common"}, {"name": "Froakie", "image": "https://images.pokemontcg.io/sm6/22.png", "number": "22", "supertype": "Pokémon", "rarity": "Common"}, {"name": "Frogadier", "image": "https://images.pokemontcg.io/sm6/23.png", "number": "23", "supertype": "Pokémon", "rarity": "Common"}, {"name": "Greninja GX", "image": "https://images.pokemontcg.io/sm6/24.png", "number": "24", "supertype": "Pokémon", "rarity": "Common"}, {"name": "Clauncher", "image": "https://images.pokemontcg.io/sm6/25.png", "number": "25", "supertype": "Pokémon", "rarity": "Common"}, {"name": "Clawitzer", "image": "https://images.pokemontcg.io/sm6/26.png", "number": "26", "supertype": "Pokémon", "rarity": "Common"}, {"name": "Amaura", "image": "https://images.pokemontcg.io/sm6/27.png", "number": "27", "supertype": "Pokémon", "rarity": "Common"}, {"name": "Aurorus", "image": "https://images.pokemontcg.io/sm6/28.png", "number": "28", "supertype": "Pokémon", "rarity": "Common"}, {"name": "Bergmite", "image": "https://images.pokemontcg.io/sm6/29.png", "number": "29", "supertype": "Pokémon", "rarity": "Common"}, {"name": "Avalugg", "image": "https://images.pokemontcg.io/sm6/30.png", "number": "30", "supertype": "Pokémon", "rarity": "Common"}, {"name": "Volcanion ◇", "image": "https://images.pokemontcg.io/sm6/31.png", "number": "31", "supertype": "Pokémon", "rarity": "Common"}, {"name": "Dewpider", "image": "https://images.pokemontcg.io/sm6/32.png", "number": "32", "supertype": "Pokémon", "rarity": "Common"}, {"name": "Araquanid", "image": "https://images.pokemontcg.io/sm6/33.png", "number": "33", "supertype": "Pokémon", "rarity": "Common"}, {"name": "Magnemite", "image": "https://images.pokemontcg.io/sm6/34.png", "number": "34", "supertype": "Pokémon", "rarity": "Common"}, {"name": "Magneton", "image": "https://images.pokemontcg.io/sm6/35.png", "number": "35", "supertype": "Pokémon", "rarity": "Common"}, {"name": "Magnezone", "image": "https://images.pokemontcg.io/sm6/36.png", "number": "36", "supertype": "Pokémon", "rarity": "Common"}, {"name": "Helioptile", "image": "https://images.pokemontcg.io/sm6/37.png", "number": "37", "supertype": "Pokémon", "rarity": "Common"}, {"name": "Heliolisk", "image": "https://images.pokemontcg.io/sm6/38.png", "number": "38", "supertype": "Pokémon", "rarity": "Common"}, {"name": "Xurkitree", "image": "https://images.pokemontcg.io/sm6/39.png", "number": "39", "supertype": "Pokémon", "rarity": "Common"}, {"name": "Rotom", "image": "https://images.pokemontcg.io/sm6/40.png", "number": "40", "supertype": "Pokémon", "rarity": "Common"}, {"name": "Uxie", "image": "https://images.pokemontcg.io/sm6/41.png", "number": "41", "supertype": "Pokémon", "rarity": "Common"}, {"name": "Mesprit", "image": "https://images.pokemontcg.io/sm6/42.png", "number": "42", "supertype": "Pokémon", "rarity": "Common"}, {"name": "Azelf", "image": "https://images.pokemontcg.io/sm6/43.png", "number": "43", "supertype": "Pokémon", "rarity": "Common"}, {"name": "Espurr", "image": "https://images.pokemontcg.io/sm6/44.png", "number": "44", "supertype": "Pokémon", "rarity": "Common"}, {"name": "Meowstic", "image": "https://images.pokemontcg.io/sm6/45.png", "number": "45", "supertype": "Pokémon", "rarity": "Common"}, {"name": "Honedge", "image": "https://images.pokemontcg.io/sm6/46.png", "number": "46", "supertype": "Pokémon", "rarity": "Common"}, {"name": "Honedge", "image": "https://images.pokemontcg.io/sm6/47.png", "number": "47", "supertype": "Pokémon", "rarity": "Common"}, {"name": "Doublade", "image": "https://images.pokemontcg.io/sm6/48.png", "number": "48", "supertype": "Pokémon", "rarity": "Common"}, {"name": "Aegislash", "image": "https://images.pokemontcg.io/sm6/49.png", "number": "49", "supertype": "Pokémon", "rarity": "Common"}, {"name": "Inkay", "image": "https://images.pokemontcg.io/sm6/50.png", "number": "50", "supertype": "Pokémon", "rarity": "Common"}, {"name": "Malamar", "image": "https://images.pokemontcg.io/sm6/51.png", "number": "51", "supertype": "Pokémon", "rarity": "Common"}, {"name": "Skrelp", "image": "https://images.pokemontcg.io/sm6/52.png", "number": "52", "supertype": "Pokémon", "rarity": "Common"}, {"name": "Dragalge", "image": "https://images.pokemontcg.io/sm6/53.png", "number": "53", "supertype": "Pokémon", "rarity": "Uncommon"}, {"name": "Hoopa", "image": "https://images.pokemontcg.io/sm6/54.png", "number": "54", "supertype": "Pokémon", "rarity": "Uncommon"}, {"name": "Poipole", "image": "https://images.pokemontcg.io/sm6/55.png", "number": "55", "supertype": "Pokémon", "rarity": "Uncommon"}, {"name": "Naganadel GX", "image": "https://images.pokemontcg.io/sm6/56.png", "number": "56", "supertype": "Pokémon", "rarity": "Uncommon"}, {"name": "Cubone", "image": "https://images.pokemontcg.io/sm6/57.png", "number": "57", "supertype": "Pokémon", "rarity": "Uncommon"}, {"name": "Torterra", "image": "https://images.pokemontcg.io/sm6/58.png", "number": "58", "supertype": "Pokémon", "rarity": "Uncommon"}, {"name": "Infernape", "image": "https://images.pokemontcg.io/sm6/59.png", "number": "59", "supertype": "Pokémon", "rarity": "Uncommon"}, {"name": "Gible", "image": "https://images.pokemontcg.io/sm6/60.png", "number": "60", "supertype": "Pokémon", "rarity": "Uncommon"}, {"name": "Gabite", "image": "https://images.pokemontcg.io/sm6/61.png", "number": "61", "supertype": "Pokémon", "rarity": "Uncommon"}, {"name": "Garchomp", "image": "https://images.pokemontcg.io/sm6/62.png", "number": "62", "supertype": "Pokémon", "rarity": "Uncommon"}, {"name": "Croagunk", "image": "https://images.pokemontcg.io/sm6/63.png", "number": "63", "supertype": "Pokémon", "rarity": "Uncommon"}, {"name": "Toxicroak", "image": "https://images.pokemontcg.io/sm6/64.png", "number": "64", "supertype": "Pokémon", "rarity": "Uncommon"}, {"name": "Pancham", "image": "https://images.pokemontcg.io/sm6/65.png", "number": "65", "supertype": "Pokémon", "rarity": "Uncommon"}, {"name": "Binacle", "image": "https://images.pokemontcg.io/sm6/66.png", "number": "66", "supertype": "Pokémon", "rarity": "Uncommon"}, {"name": "Barbaracle", "image": "https://images.pokemontcg.io/sm6/67.png", "number": "67", "supertype": "Pokémon", "rarity": "Uncommon"}, {"name": "Tyrunt", "image": "https://images.pokemontcg.io/sm6/68.png", "number": "68", "supertype": "Pokémon", "rarity": "Uncommon"}, {"name": "Tyrantrum", "image": "https://images.pokemontcg.io/sm6/69.png", "number": "69", "supertype": "Pokémon", "rarity": "Uncommon"}, {"name": "Hawlucha", "image": "https://images.pokemontcg.io/sm6/70.png", "number": "70", "supertype": "Pokémon", "rarity": "Uncommon"}, {"name": "Zygarde", "image": "https://images.pokemontcg.io/sm6/71.png", "number": "71", "supertype": "Pokémon", "rarity": "Uncommon"}, {"name": "Zygarde", "image": "https://images.pokemontcg.io/sm6/72.png", "number": "72", "supertype": "Pokémon", "rarity": "Uncommon"}, {"name": "Zygarde GX", "image": "https://images.pokemontcg.io/sm6/73.png", "number": "73", "supertype": "Pokémon", "rarity": "Uncommon"}, {"name": "Diancie ◇", "image": "https://images.pokemontcg.io/sm6/74.png", "number": "74", "supertype": "Pokémon", "rarity": "Uncommon"}, {"name": "Rockruff", "image": "https://images.pokemontcg.io/sm6/75.png", "number": "75", "supertype": "Pokémon", "rarity": "Uncommon"}, {"name": "Lycanroc", "image": "https://images.pokemontcg.io/sm6/76.png", "number": "76", "supertype": "Pokémon", "rarity": "Uncommon"}, {"name": "Buzzwole", "image": "https://images.pokemontcg.io/sm6/77.png", "number": "77", "supertype": "Pokémon", "rarity": "Uncommon"}, {"name": "Pangoro", "image": "https://images.pokemontcg.io/sm6/78.png", "number": "78", "supertype": "Pokémon", "rarity": "Uncommon"}, {"name": "Yveltal GX", "image": "https://images.pokemontcg.io/sm6/79.png", "number": "79", "supertype": "Pokémon", "rarity": "Uncommon"}, {"name": "Guzzlord", "image": "https://images.pokemontcg.io/sm6/80.png", "number": "80", "supertype": "Pokémon", "rarity": "Uncommon"}, {"name": "Empoleon", "image": "https://images.pokemontcg.io/sm6/81.png", "number": "81", "supertype": "Pokémon", "rarity": "Uncommon"}, {"name": "Dialga GX", "image": "https://images.pokemontcg.io/sm6/82.png", "number": "82", "supertype": "Pokémon", "rarity": "Rare"}, {"name": "Flabébé", "image": "https://images.pokemontcg.io/sm6/83.png", "number": "83", "supertype": "Pokémon", "rarity": "Rare"}, {"name": "Flabébé", "image": "https://images.pokemontcg.io/sm6/84.png", "number": "84", "supertype": "Pokémon", "rarity": "Rare"}, {"name": "Floette", "image": "https://images.pokemontcg.io/sm6/85.png", "number": "85", "supertype": "Pokémon", "rarity": "Rare"}, {"name": "Florges", "image": "https://images.pokemontcg.io/sm6/86.png", "number": "86", "supertype": "Pokémon", "rarity": "Rare"}, {"name": "Sylveon", "image": "https://images.pokemontcg.io/sm6/87.png", "number": "87", "supertype": "Pokémon", "rarity": "Rare"}, {"name": "Dedenne", "image": "https://images.pokemontcg.io/sm6/88.png", "number": "88", "supertype": "Pokémon", "rarity": "Rare"}, {"name": "Klefki", "image": "https://images.pokemontcg.io/sm6/89.png", "number": "89", "supertype": "Pokémon", "rarity": "Rare"}, {"name": "Xerneas GX", "image": "https://images.pokemontcg.io/sm6/90.png", "number": "90", "supertype": "Pokémon", "rarity": "Rare"}, {"name": "Goomy", "image": "https://images.pokemontcg.io/sm6/91.png", "number": "91", "supertype": "Pokémon", "rarity": "Rare"}, {"name": "Goomy", "image": "https://images.pokemontcg.io/sm6/92.png", "number": "92", "supertype": "Pokémon", "rarity": "Rare"}, {"name": "Sliggoo", "image": "https://images.pokemontcg.io/sm6/93.png", "number": "93", "supertype": "Pokémon", "rarity": "Rare"}, {"name": "Goodra", "image": "https://images.pokemontcg.io/sm6/94.png", "number": "94", "supertype": "Pokémon", "rarity": "Rare"}, {"name": "Ultra Necrozma GX", "image": "https://images.pokemontcg.io/sm6/95.png", "number": "95", "supertype": "Pokémon", "rarity": "Rare"}, {"name": "Arceus ◇", "image": "https://images.pokemontcg.io/sm6/96.png", "number": "96", "supertype": "Pokémon", "rarity": "Rare"}, {"name": "Bunnelby", "image": "https://images.pokemontcg.io/sm6/97.png", "number": "97", "supertype": "Pokémon", "rarity": "Rare"}, {"name": "Diggersby", "image": "https://images.pokemontcg.io/sm6/98.png", "number": "98", "supertype": "Pokémon", "rarity": "Rare"}, {"name": "Furfrou", "image": "https://images.pokemontcg.io/sm6/99.png", "number": "99", "supertype": "Pokémon", "rarity": "Rare"}, {"name": "Noibat", "image": "https://images.pokemontcg.io/sm6/100.png", "number": "100", "supertype": "Pokémon", "rarity": "Rare"}, {"name": "Noivern", "image": "https://images.pokemontcg.io/sm6/101.png", "number": "101", "supertype": "Pokémon", "rarity": "Rare"}, {"name": "Beast Ring", "image": "https://images.pokemontcg.io/sm6/102.png", "number": "102", "supertype": "Pokémon", "rarity": "Rare"}, {"name": "Bonnie", "image": "https://images.pokemontcg.io/sm6/103.png", "number": "103", "supertype": "Pokémon", "rarity": "Rare"}, {"name": "Crasher Wake", "image": "https://images.pokemontcg.io/sm6/104.png", "number": "104", "supertype": "Pokémon", "rarity": "Double Rare"}, {"name": "Diantha", "image": "https://images.pokemontcg.io/sm6/105.png", "number": "105", "supertype": "Pokémon", "rarity": "Double Rare"}, {"name": "Eneporter", "image": "https://images.pokemontcg.io/sm6/106.png", "number": "106", "supertype": "Pokémon", "rarity": "Double Rare"}, {"name": "Fossil Excavation Map", "image": "https://images.pokemontcg.io/sm6/107.png", "number": "107", "supertype": "Pokémon", "rarity": "Double Rare"}, {"name": "Judge", "image": "https://images.pokemontcg.io/sm6/108.png", "number": "108", "supertype": "Pokémon", "rarity": "Double Rare"}, {"name": "Lady", "image": "https://images.pokemontcg.io/sm6/109.png", "number": "109", "supertype": "Pokémon", "rarity": "Double Rare"}, {"name": "Lysandre ◇", "image": "https://images.pokemontcg.io/sm6/110.png", "number": "110", "supertype": "Pokémon", "rarity": "Double Rare"}, {"name": "Lysandre Labs", "image": "https://images.pokemontcg.io/sm6/111.png", "number": "111", "supertype": "Pokémon", "rarity": "Double Rare"}, {"name": "Metal Frying Pan", "image": "https://images.pokemontcg.io/sm6/112.png", "number": "112", "supertype": "Pokémon", "rarity": "Double Rare"}, {"name": "Mysterious Treasure", "image": "https://images.pokemontcg.io/sm6/113.png", "number": "113", "supertype": "Pokémon", "rarity": "Double Rare"}, {"name": "Ultra Recon Squad", "image": "https://images.pokemontcg.io/sm6/114.png", "number": "114", "supertype": "Pokémon", "rarity": "Double Rare"}, {"name": "Ultra Space", "image": "https://images.pokemontcg.io/sm6/115.png", "number": "115", "supertype": "Pokémon", "rarity": "Double Rare"}, {"name": "Unidentified Fossil", "image": "https://images.pokemontcg.io/sm6/116.png", "number": "116", "supertype": "Pokémon", "rarity": "Double Rare"}, {"name": "Beast Energy ◇", "image": "https://images.pokemontcg.io/sm6/117.png", "number": "117", "supertype": "Pokémon", "rarity": "Double Rare"}, {"name": "Unit Energy FightingDarknessFairy", "image": "https://images.pokemontcg.io/sm6/118.png", "number": "118", "supertype": "Pokémon", "rarity": "Illustration Rare"}, {"name": "Palkia GX", "image": "https://images.pokemontcg.io/sm6/119.png", "number": "119", "supertype": "Pokémon", "rarity": "Illustration Rare"}, {"name": "Greninja GX", "image": "https://images.pokemontcg.io/sm6/120.png", "number": "120", "supertype": "Pokémon", "rarity": "Illustration Rare"}, {"name": "Naganadel GX", "image": "https://images.pokemontcg.io/sm6/121.png", "number": "121", "supertype": "Pokémon", "rarity": "Illustration Rare"}, {"name": "Lucario GX", "image": "https://images.pokemontcg.io/sm6/122.png", "number": "122", "supertype": "Pokémon", "rarity": "Illustration Rare"}, {"name": "Zygarde GX", "image": "https://images.pokemontcg.io/sm6/123.png", "number": "123", "supertype": "Pokémon", "rarity": "Illustration Rare"}, {"name": "Yveltal GX", "image": "https://images.pokemontcg.io/sm6/124.png", "number": "124", "supertype": "Pokémon", "rarity": "Illustration Rare"}, {"name": "Dialga GX", "image": "https://images.pokemontcg.io/sm6/125.png", "number": "125", "supertype": "Pokémon", "rarity": "Illustration Rare"}, {"name": "Xerneas GX", "image": "https://images.pokemontcg.io/sm6/126.png", "number": "126", "supertype": "Pokémon", "rarity": "Illustration Rare"}, {"name": "Ultra Necrozma GX", "image": "https://images.pokemontcg.io/sm6/127.png", "number": "127", "supertype": "Pokémon", "rarity": "Illustration Rare"}, {"name": "Bonnie", "image": "https://images.pokemontcg.io/sm6/128.png", "number": "128", "supertype": "Pokémon", "rarity": "Illustration Rare"}, {"name": "Crasher Wake", "image": "https://images.pokemontcg.io/sm6/129.png", "number": "129", "supertype": "Pokémon", "rarity": "Illustration Rare"}, {"name": "Diantha", "image": "https://images.pokemontcg.io/sm6/130.png", "number": "130", "supertype": "Pokémon", "rarity": "Ultra Rare"}, {"name": "Ultra Recon Squad", "image": "https://images.pokemontcg.io/sm6/131.png", "number": "131", "supertype": "Pokémon", "rarity": "Ultra Rare"}, {"name": "Palkia GX", "image": "https://images.pokemontcg.io/sm6/132.png", "number": "132", "supertype": "Pokémon", "rarity": "Ultra Rare"}, {"name": "Greninja GX", "image": "https://images.pokemontcg.io/sm6/133.png", "number": "133", "supertype": "Pokémon", "rarity": "Ultra Rare"}, {"name": "Naganadel GX", "image": "https://images.pokemontcg.io/sm6/134.png", "number": "134", "supertype": "Pokémon", "rarity": "Ultra Rare"}, {"name": "Lucario GX", "image": "https://images.pokemontcg.io/sm6/135.png", "number": "135", "supertype": "Pokémon", "rarity": "Ultra Rare"}, {"name": "Zygarde GX", "image": "https://images.pokemontcg.io/sm6/136.png", "number": "136", "supertype": "Pokémon", "rarity": "Ultra Rare"}, {"name": "Yveltal GX", "image": "https://images.pokemontcg.io/sm6/137.png", "number": "137", "supertype": "Pokémon", "rarity": "Ultra Rare"}, {"name": "Dialga GX", "image": "https://images.pokemontcg.io/sm6/138.png", "number": "138", "supertype": "Pokémon", "rarity": "Ultra Rare"}, {"name": "Xerneas GX", "image": "https://images.pokemontcg.io/sm6/139.png", "number": "139", "supertype": "Pokémon", "rarity": "Special Illustration Rare"}, {"name": "Ultra Necrozma GX", "image": "https://images.pokemontcg.io/sm6/140.png", "number": "140", "supertype": "Pokémon", "rarity": "Special Illustration Rare"}, {"name": "Beast Ring", "image": "https://images.pokemontcg.io/sm6/141.png", "number": "141", "supertype": "Pokémon", "rarity": "Special Illustration Rare"}, {"name": "Eneporter", "image": "https://images.pokemontcg.io/sm6/142.png", "number": "142", "supertype": "Pokémon", "rarity": "Special Illustration Rare"}, {"name": "Energy Recycler", "image": "https://images.pokemontcg.io/sm6/143.png", "number": "143", "supertype": "Pokémon", "rarity": "Special Illustration Rare"}, {"name": "Metal Frying Pan", "image": "https://images.pokemontcg.io/sm6/144.png", "number": "144", "supertype": "Pokémon", "rarity": "Special Illustration Rare"}, {"name": "Mysterious Treasure", "image": "https://images.pokemontcg.io/sm6/145.png", "number": "145", "supertype": "Pokémon", "rarity": "Hyper Rare"}, {"name": "Unit Energy FightingDarknessFairy", "image": "https://images.pokemontcg.io/sm6/146.png", "number": "146", "supertype": "Pokémon", "rarity": "Hyper Rare"}]}