{"name": "heartgold-soulsilver", "displayName": "HeartGold SoulSilver", "id": "hgss1", "cards": [{"name": "Arcanine", "image": "", "number": "1", "supertype": "Pokémon", "rarity": "Common"}, {"name": "Azumarill", "image": "", "number": "2", "supertype": "Pokémon", "rarity": "Common"}, {"name": "Clefable", "image": "", "number": "3", "supertype": "Pokémon", "rarity": "Common"}, {"name": "Gyarados", "image": "", "number": "4", "supertype": "Pokémon", "rarity": "Common"}, {"name": "Hitmontop", "image": "", "number": "5", "supertype": "Pokémon", "rarity": "Common"}, {"name": "Jumpluff", "image": "", "number": "6", "supertype": "Pokémon", "rarity": "Common"}, {"name": "Ninetales", "image": "", "number": "7", "supertype": "Pokémon", "rarity": "Common"}, {"name": "Noctowl", "image": "", "number": "8", "supertype": "Pokémon", "rarity": "Common"}, {"name": "Quagsire", "image": "", "number": "9", "supertype": "Pokémon", "rarity": "Common"}, {"name": "Raichu", "image": "", "number": "10", "supertype": "Pokémon", "rarity": "Common"}, {"name": "Shuckle", "image": "", "number": "11", "supertype": "Pokémon", "rarity": "Common"}, {"name": "Slowking", "image": "", "number": "12", "supertype": "Pokémon", "rarity": "Common"}, {"name": "Wobbuffet", "image": "", "number": "13", "supertype": "Pokémon", "rarity": "Common"}, {"name": "Ampharos", "image": "", "number": "14", "supertype": "Pokémon", "rarity": "Common"}, {"name": "Ariados", "image": "", "number": "15", "supertype": "Pokémon", "rarity": "Common"}, {"name": "Butterfree", "image": "", "number": "16", "supertype": "Pokémon", "rarity": "Common"}, {"name": "Cleffa", "image": "", "number": "17", "supertype": "Pokémon", "rarity": "Common"}, {"name": "Exeggutor", "image": "", "number": "18", "supertype": "Pokémon", "rarity": "Common"}, {"name": "Farfetch’d", "image": "", "number": "19", "supertype": "Pokémon", "rarity": "Common"}, {"name": "Feraligatr", "image": "", "number": "20", "supertype": "Pokémon", "rarity": "Common"}, {"name": "Furret", "image": "", "number": "21", "supertype": "Pokémon", "rarity": "Common"}, {"name": "Granbull", "image": "", "number": "22", "supertype": "Pokémon", "rarity": "Common"}, {"name": "Hypno", "image": "", "number": "23", "supertype": "Pokémon", "rarity": "Common"}, {"name": "Lapras", "image": "", "number": "24", "supertype": "Pokémon", "rarity": "Common"}, {"name": "Ledian", "image": "", "number": "25", "supertype": "Pokémon", "rarity": "Common"}, {"name": "Meganium", "image": "", "number": "26", "supertype": "Pokémon", "rarity": "Common"}, {"name": "Persian", "image": "", "number": "27", "supertype": "Pokémon", "rarity": "Common"}, {"name": "Pichu", "image": "", "number": "28", "supertype": "Pokémon", "rarity": "Common"}, {"name": "Sandslash", "image": "", "number": "29", "supertype": "Pokémon", "rarity": "Common"}, {"name": "Smoochum", "image": "", "number": "30", "supertype": "Pokémon", "rarity": "Common"}, {"name": "Sunflora", "image": "", "number": "31", "supertype": "Pokémon", "rarity": "Common"}, {"name": "Typhlosion", "image": "", "number": "32", "supertype": "Pokémon", "rarity": "Common"}, {"name": "Tyrogue", "image": "", "number": "33", "supertype": "Pokémon", "rarity": "Common"}, {"name": "Weezing", "image": "", "number": "34", "supertype": "Pokémon", "rarity": "Common"}, {"name": "Bayleef", "image": "", "number": "35", "supertype": "Pokémon", "rarity": "Common"}, {"name": "Blissey", "image": "", "number": "36", "supertype": "Pokémon", "rarity": "Common"}, {"name": "Corsola", "image": "", "number": "37", "supertype": "Pokémon", "rarity": "Common"}, {"name": "Croconaw", "image": "", "number": "38", "supertype": "Pokémon", "rarity": "Common"}, {"name": "Delibird", "image": "", "number": "39", "supertype": "Pokémon", "rarity": "Common"}, {"name": "Donphan", "image": "", "number": "40", "supertype": "Pokémon", "rarity": "Common"}, {"name": "Dunsparce", "image": "", "number": "41", "supertype": "Pokémon", "rarity": "Common"}, {"name": "Flaaffy", "image": "", "number": "42", "supertype": "Pokémon", "rarity": "Common"}, {"name": "Heracross", "image": "", "number": "43", "supertype": "Pokémon", "rarity": "Common"}, {"name": "Igglybuff", "image": "", "number": "44", "supertype": "Pokémon", "rarity": "Common"}, {"name": "Mantine", "image": "", "number": "45", "supertype": "Pokémon", "rarity": "Uncommon"}, {"name": "Metapod", "image": "", "number": "46", "supertype": "Pokémon", "rarity": "Uncommon"}, {"name": "Miltank", "image": "", "number": "47", "supertype": "Pokémon", "rarity": "Uncommon"}, {"name": "Parasect", "image": "", "number": "48", "supertype": "Pokémon", "rarity": "Uncommon"}, {"name": "Quilava", "image": "", "number": "49", "supertype": "Pokémon", "rarity": "Uncommon"}, {"name": "Qwilfish", "image": "", "number": "50", "supertype": "Pokémon", "rarity": "Uncommon"}, {"name": "Skiploom", "image": "", "number": "51", "supertype": "Pokémon", "rarity": "Uncommon"}, {"name": "Slowbro", "image": "", "number": "52", "supertype": "Pokémon", "rarity": "Uncommon"}, {"name": "Starmie", "image": "", "number": "53", "supertype": "Pokémon", "rarity": "Uncommon"}, {"name": "Unown", "image": "", "number": "54", "supertype": "Pokémon", "rarity": "Uncommon"}, {"name": "Unown", "image": "", "number": "55", "supertype": "Pokémon", "rarity": "Uncommon"}, {"name": "Wigglytuff", "image": "", "number": "56", "supertype": "Pokémon", "rarity": "Uncommon"}, {"name": "Caterpie", "image": "", "number": "57", "supertype": "Pokémon", "rarity": "Uncommon"}, {"name": "Chansey", "image": "", "number": "58", "supertype": "Pokémon", "rarity": "Uncommon"}, {"name": "Chikorita", "image": "", "number": "59", "supertype": "Pokémon", "rarity": "Uncommon"}, {"name": "Clefairy", "image": "", "number": "60", "supertype": "Pokémon", "rarity": "Uncommon"}, {"name": "Cyndaquil", "image": "", "number": "61", "supertype": "Pokémon", "rarity": "Uncommon"}, {"name": "Drowzee", "image": "", "number": "62", "supertype": "Pokémon", "rarity": "Uncommon"}, {"name": "Exeggcute", "image": "", "number": "63", "supertype": "Pokémon", "rarity": "Uncommon"}, {"name": "Girafarig", "image": "", "number": "64", "supertype": "Pokémon", "rarity": "Uncommon"}, {"name": "Growlithe", "image": "", "number": "65", "supertype": "Pokémon", "rarity": "Uncommon"}, {"name": "Hoothoot", "image": "", "number": "66", "supertype": "Pokémon", "rarity": "Uncommon"}, {"name": "Hoppip", "image": "", "number": "67", "supertype": "Pokémon", "rarity": "Uncommon"}, {"name": "Jigglypuff", "image": "", "number": "68", "supertype": "Pokémon", "rarity": "Uncommon"}, {"name": "Jynx", "image": "", "number": "69", "supertype": "Pokémon", "rarity": "Uncommon"}, {"name": "Koffing", "image": "", "number": "70", "supertype": "Pokémon", "rarity": "Rare"}, {"name": "Ledyba", "image": "", "number": "71", "supertype": "Pokémon", "rarity": "Rare"}, {"name": "Magikarp", "image": "", "number": "72", "supertype": "Pokémon", "rarity": "Rare"}, {"name": "Mareep", "image": "", "number": "73", "supertype": "Pokémon", "rarity": "Rare"}, {"name": "Marill", "image": "", "number": "74", "supertype": "Pokémon", "rarity": "Rare"}, {"name": "Meowth", "image": "", "number": "75", "supertype": "Pokémon", "rarity": "Rare"}, {"name": "Paras", "image": "", "number": "76", "supertype": "Pokémon", "rarity": "Rare"}, {"name": "Phanpy", "image": "", "number": "77", "supertype": "Pokémon", "rarity": "Rare"}, {"name": "Pikachu", "image": "", "number": "78", "supertype": "Pokémon", "rarity": "Rare"}, {"name": "Sandshrew", "image": "", "number": "79", "supertype": "Pokémon", "rarity": "Rare"}, {"name": "Sentret", "image": "", "number": "80", "supertype": "Pokémon", "rarity": "Rare"}, {"name": "Slowpoke", "image": "", "number": "81", "supertype": "Pokémon", "rarity": "Rare"}, {"name": "Snubbull", "image": "", "number": "82", "supertype": "Pokémon", "rarity": "Rare"}, {"name": "Spinarak", "image": "", "number": "83", "supertype": "Pokémon", "rarity": "Rare"}, {"name": "Staryu", "image": "", "number": "84", "supertype": "Pokémon", "rarity": "Rare"}, {"name": "Sunkern", "image": "", "number": "85", "supertype": "Pokémon", "rarity": "Rare"}, {"name": "Totodile", "image": "", "number": "86", "supertype": "Pokémon", "rarity": "Rare"}, {"name": "Vulpix", "image": "", "number": "87", "supertype": "Pokémon", "rarity": "Rare"}, {"name": "Wooper", "image": "", "number": "88", "supertype": "Pokémon", "rarity": "Double Rare"}, {"name": "Bill", "image": "", "number": "89", "supertype": "Pokémon", "rarity": "Double Rare"}, {"name": "Copycat", "image": "", "number": "90", "supertype": "Pokémon", "rarity": "Double Rare"}, {"name": "Energy Switch", "image": "", "number": "91", "supertype": "Pokémon", "rarity": "Double Rare"}, {"name": "Fisherman", "image": "", "number": "92", "supertype": "Pokémon", "rarity": "Double Rare"}, {"name": "Full Heal", "image": "", "number": "93", "supertype": "Pokémon", "rarity": "Double Rare"}, {"name": "Moomoo Milk", "image": "", "number": "94", "supertype": "Pokémon", "rarity": "Double Rare"}, {"name": "Poké Ball", "image": "", "number": "95", "supertype": "Pokémon", "rarity": "Double Rare"}, {"name": "Pokégear3.0", "image": "", "number": "96", "supertype": "Pokémon", "rarity": "Double Rare"}, {"name": "Pokémon Collector", "image": "", "number": "97", "supertype": "Pokémon", "rarity": "Double Rare"}, {"name": "Pokémon Communication", "image": "", "number": "98", "supertype": "Pokémon", "rarity": "Double Rare"}, {"name": "Pokémon Reversal", "image": "", "number": "99", "supertype": "Pokémon", "rarity": "Double Rare"}, {"name": "Professor Elm’s Training Method", "image": "", "number": "100", "supertype": "Pokémon", "rarity": "Double Rare"}, {"name": "Professor Oak’s New Theory", "image": "", "number": "101", "supertype": "Pokémon", "rarity": "Illustration Rare"}, {"name": "Switch", "image": "", "number": "102", "supertype": "Pokémon", "rarity": "Illustration Rare"}, {"name": "Double Colorless Energy", "image": "", "number": "103", "supertype": "Pokémon", "rarity": "Illustration Rare"}, {"name": "Rainbow Energy", "image": "", "number": "104", "supertype": "Pokémon", "rarity": "Illustration Rare"}, {"name": "Ampharos", "image": "", "number": "105", "supertype": "Pokémon", "rarity": "Illustration Rare"}, {"name": "Blissey", "image": "", "number": "106", "supertype": "Pokémon", "rarity": "Illustration Rare"}, {"name": "Donphan", "image": "", "number": "107", "supertype": "Pokémon", "rarity": "Illustration Rare"}, {"name": "Feraligatr", "image": "", "number": "108", "supertype": "Pokémon", "rarity": "Illustration Rare"}, {"name": "Meganium", "image": "", "number": "109", "supertype": "Pokémon", "rarity": "Illustration Rare"}, {"name": "Typhlosion", "image": "", "number": "110", "supertype": "Pokémon", "rarity": "Illustration Rare"}, {"name": "Ho-Oh LEGEND", "image": "", "number": "111", "supertype": "Pokémon", "rarity": "Ultra Rare"}, {"name": "Ho-Oh LEGEND", "image": "", "number": "112", "supertype": "Pokémon", "rarity": "Ultra Rare"}, {"name": "Lugia LEGEND", "image": "", "number": "113", "supertype": "Pokémon", "rarity": "Ultra Rare"}, {"name": "Lugia LEGEND", "image": "", "number": "114", "supertype": "Pokémon", "rarity": "Ultra Rare"}, {"name": "Grass Energy", "image": "", "number": "115", "supertype": "Pokémon", "rarity": "Ultra Rare"}, {"name": "Fire Energy", "image": "", "number": "116", "supertype": "Pokémon", "rarity": "Ultra Rare"}, {"name": "Water Energy", "image": "", "number": "117", "supertype": "Pokémon", "rarity": "Ultra Rare"}, {"name": "Lightning Energy", "image": "", "number": "118", "supertype": "Pokémon", "rarity": "Special Illustration Rare"}, {"name": "Psychic Energy", "image": "", "number": "119", "supertype": "Pokémon", "rarity": "Special Illustration Rare"}, {"name": "Fighting Energy", "image": "", "number": "120", "supertype": "Pokémon", "rarity": "Special Illustration Rare"}, {"name": "Darkness Energy", "image": "", "number": "121", "supertype": "Pokémon", "rarity": "Special Illustration Rare"}, {"name": "Metal Energy", "image": "", "number": "122", "supertype": "Pokémon", "rarity": "Special Illustration Rare"}, {"name": "Gyarados", "image": "", "number": "123", "supertype": "Pokémon", "rarity": "Hyper Rare"}, {"name": "Alph Lithograph", "image": "", "number": "ONE", "supertype": "Pokémon", "rarity": "Hyper Rare"}]}